Workbook
Name ACQUISITION_COST: #REF!
Name AMORTIZATION: #REF!
Name Corporate: #REF!
Name COST_OF_GOODS___SERVICES: #REF!
Name EXCESS: #REF!
Name EXTRAORDINARY_INCOME____EXPENSE: #REF!
Name General_and_Administration: #REF!
Name Gross_Profit: #REF!
Name INCOME_BEFORE_INTEREST___TAXES: #REF!
Name INCOME_FROM_OPERATIONS: #REF!
Name INTEREST__EXPENSE: #REF!
Name Month1: SalesMktg!$B$8
Name Month10: SalesMktg!$K$8
Name Month11: SalesMktg!$L$8
Name Month12: SalesMktg!$M$8
Name Month2: SalesMktg!$C$8
Name Month3: SalesMktg!$D$8
Name Month4: SalesMktg!$E$8
Name Month5: SalesMktg!$F$8
Name Month6: SalesMktg!$G$8
Name Month7: SalesMktg!$H$8
Name Month8: SalesMktg!$I$8
Name Month9: SalesMktg!$J$8
Name NET_INCOME_BEFORE_TAXES: #REF!
Name NET_REVENUES: #REF!
Name of_Revenue: #REF!
Name of_Revenues: #REF!
Name OPER_EXP_TO_REV: #REF!
Name OPERATING_EXPENSES: #REF!
Name Research_and_Development: #REF!
Name Sales_and_Marketing: #REF!
Name STD: #REF!
Name TECH_SUP_COMP: #REF!
Name TECH_SUPPORT: #REF!
Name Technical_Support: #REF!
Name Total_Operating_Expenses: #REF!
Name Total_Product_Sales: #REF!
Name Total_Service_Revenue: #REF!
Name TOTALOTHERASSETS: #REF!
Name Venture: 'Unit Economics'!$A$1
Name Year_1: SalesMktg!$N$8
Name Year1: SalesMktg!$N$8
Name Year2: SalesMktg!$O$8
Name Year3: SalesMktg!$P$8

Sheet SalesMktg
A1: =Venture -> FitBox
A2: Sales & Marketing Expenses
A3: Develop a list of general and conversion marketing activities.
A4: Think about how the number & type of marketing activities and conversion work together to yield customers (EX. X emails-->y meetings & demo-->sale
A5: Provide rates to convert prospects from one activity to the next.
A6: Create yours on this worksheet and be sure that the bottom line sales & marketing expense is reflected in the monthly and annual sums highlighted in yellow. These will be referenced in the P&L worksheet.
A8: Marketing activities | B8: 45505 | C8: 45536 | D8: 45566 | E8: 45597 | F8: 45627 | G8: 45658 | H8: 45689 | I8: 45717 | J8: 45748 | K8: 45778 | L8: 45809 | M8: 45839 | N8: 2024-25 | O8: 2025-26 | P8: 2026-27
A9: General sales & marketing expense
A10: [these activities support the company and existing customers and may not lead directly to new customers. Enter activity description & cost.]
A11: TikTok/Instagram/Viral Videos | B11: 500 | C11: 500 | D11: 500 | E11: 500 | F11: 500 | G11: 800 | H11: 800 | I11: 800 | J11: 800 | K11: 800 | L11: 500 | M11: 500 | N11: =SUM(B11:M11) -> 7500 | O11: 10000 | P11: 13000
A12: On-campus exhibitons such as during PE classes | B12: 300 | C12: 300 | D12: 300 | E12: 300 | F12: 300 | G12: 300 | H12: 300 | I12: 300 | J12: 300 | K12: 300 | L12: 300 | M12: 300 | N12: =SUM(B12:M12) -> 3600 | O12: 5000 | P12: 7000
A13: Initial Discounts | B13: 820 | C13: 820 | D13: 820 | E13: 820 | F13: 820 | G13: 820 | H13: 820 | I13: 820 | J13: 820 | K13: 820 | L13: 820 | M13: 820 | N13: =SUM(B13:M13) -> 9840 | O13: 13000 | P13: 20000
A14: Fitness Influencers | B14: 320 | C14: 320 | D14: 320 | E14: 320 | F14: 320 | G14: 320 | H14: 320 | I14: 320 | J14: 320 | K14: 320 | L14: 320 | M14: 320 | N14: =SUM(B14:M14) -> 3840 | O14: 5000 | P14: 10000
A16: Total general sales & marketing | B16: =SUM(B11:B14) -> 1940 | C16: =SUM(C11:C14) -> 1940 | D16: =SUM(D11:D14) -> 1940 | E16: =SUM(E11:E14) -> 1940 | F16: =SUM(F11:F14) -> 1940 | G16: =SUM(G11:G14) -> 2240 | H16: =SUM(H11:H14) -> 2240 | I16: =SUM(I11:I14) -> 2240 | ... P16: =SUM(P11:P14) -> 50000
A18: Conversion activities
A19: [these activities work together to lead prospects through a pipeline, yielding a new customer. For each prospect activity, provide the expense, the number of prospects it generates, and the percentage conversion to the next activity. You may copy as many rows of propect activities as you’d like, however, the final activity, Customer Sale Activity, converts to a new customer.]
A20: TikTok/Instagram/Viral Videos | B20: 500 | C20: 500 | D20: 500 | E20: 500 | F20: 500 | G20: 800 | H20: 800 | I20: 800 | J20: 800 | K20: 800 | L20: 500 | M20: 500 | N20: =SUM(B20:M20) -> 7500 | O20: 10000 | P20: 13000
A21: Prospects | B21: =B20/8.5*1000 -> 58823.529 | C21: =C20/8.5*1000 -> 58823.529 | D21: =D20/8.5*1000 -> 58823.529 | E21: =E20/8.5*1000 -> 58823.529 | F21: =F20/8.5*1000 -> 58823.529 | G21: =G20/8.5*1000 -> 94117.647 | H21: =H20/8.5*1000 -> 94117.647 | I21: =I20/8.5*1000 -> 94117.647 | ... M21: =M20/8.5*1000 -> 58823.529 | N21: =SUM(B21:M21) -> 882352.94 | O21: 11302302 | P21: 30234123
A22: Conversion rate | B22: 0.035 | C22: 0.035 | D22: 0.035 | E22: 0.035 | F22: 0.035 | G22: 0.035 | H22: 0.035 | I22: 0.035 | J22: 0.035 | K22: 0.035 | L22: 0.035 | M22: 0.035 | N22: =IF(AVERAGE(B22:M22)=0,"n/a",AVERAGE(B22:M22)) -> 0.035 | O22: 0.035 | P22: 0.035
A23: On-campus exhibitions | B23: 300 | C23: 300 | D23: 300 | E23: 300 | F23: 300 | G23: 300 | H23: 300 | I23: 300 | J23: 300 | K23: 300 | L23: 300 | M23: 300 | N23: =SUM(B23:M23) -> 3600 | O23: 0 | P23: 0
A24: Prospects | B24: =B21*B22 -> 2058.8235 | C24: =C21*C22 -> 2058.8235 | D24: =D21*D22 -> 2058.8235 | E24: =E21*E22 -> 2058.8235 | F24: =F21*F22 -> 2058.8235 | G24: =G21*G22 -> 3294.1176 | H24: =H21*H22 -> 3294.1176 | I24: =I21*I22 -> 3294.1176 | ... M24: =M21*M22 -> 2058.8235 | N24: =SUM(B24:M24) -> 30882.353 | O24: =O21*O22 -> 395580.57 | P24: =P21*P22 -> 1058194.3
A25: Conversion rate | B25: 0.04 | C25: 0.04 | D25: 0.04 | E25: 0.04 | F25: 0.04 | G25: 0.04 | H25: 0.04 | I25: 0.04 | J25: 0.04 | K25: 0.04 | L25: 0.04 | M25: 0.04 | N25: =IF(AVERAGE(B25:M25)=0,"n/a",AVERAGE(B25:M25)) -> 0.04 | O25: 0.04 | P25: 0.04
A26: Initial Discounts | B26: 820 | C26: 820 | D26: 820 | E26: 820 | F26: 820 | G26: 820 | H26: 820 | I26: 820 | J26: 820 | K26: 820 | L26: 820 | M26: 820 | N26: =SUM(B26:M26) -> 9840 | O26: 820 | P26: 820
A27: Prospects | B27: =B24*B25 -> 82.352941 | C27: =C24*C25 -> 82.352941 | D27: =D24*D25 -> 82.352941 | E27: =E24*E25 -> 82.352941 | F27: =F24*F25 -> 82.352941 | G27: =G24*G25 -> 131.76471 | H27: =H24*H25 -> 131.76471 | I27: =I24*I25 -> 131.76471 | ... M27: =M24*M25 -> 82.352941 | N27: =SUM(B27:M27) -> 1235.2941 | O27: =O24*O25 -> 15823.223 | P27: =P24*P25 -> 42327.772
A28: Conversion rate | B28: 0.12 | C28: 0.12 | D28: 0.12 | E28: 0.12 | F28: 0.12 | G28: 0.15 | H28: 0.15 | I28: 0.15 | J28: 0.15 | K28: 0.15 | L28: 0.12 | M28: 0.12 | N28: =IF(AVERAGE(B28:M28)=0,"n/a",AVERAGE(B28:M28)) -> 0.1325 | O28: 0.14 | P28: 0.14
A29: Fitness Influencers & Micro Influencers | B29: 320 | C29: 320 | D29: 320 | E29: 320 | F29: 320 | G29: 320 | H29: 320 | I29: 320 | J29: 320 | K29: 320 | L29: 320 | M29: 320 | N29: =SUM(B29:M29) -> 3840 | O29: 4000 | P29: 5000
A30: Prospects | B30: =B27*B28 -> 9.8823529 | C30: =C27*C28 -> 9.8823529 | D30: =D27*D28 -> 9.8823529 | E30: =E27*E28 -> 9.8823529 | F30: =F27*F28 -> 9.8823529 | G30: =G27*G28 -> 19.764706 | H30: =H27*H28 -> 19.764706 | I30: =I27*I28 -> 19.764706 | ... M30: =M27*M28 -> 9.8823529 | N30: =SUM(B30:M30) -> 168 | O30: =O27*O28 -> 2215.2512 | P30: =P27*P28 -> 5925.8881
A31: Conversion rate | B31: 0.6 | C31: 0.6 | D31: 0.6 | E31: 0.6 | F31: 0.6 | G31: 0.6 | H31: 0.6 | I31: 0.6 | J31: 0.6 | K31: 0.6 | L31: 0.6 | M31: 0.6 | N31: =IF(AVERAGE(B31:M31)=0,"n/a",AVERAGE(B31:M31)) -> 0.6 | O31: 0.6 | P31: 0.6
A32: Customer sale activity | B32: 208 | C32: 208 | D32: 208 | E32: 208 | F32: 0 | G32: 0 | H32: 0 | I32: 0 | J32: 0 | K32: 0 | L32: 0 | M32: 0 | N32: =SUM(B32:M32) -> 832 | O32: 0 | P32: 0
A33: Prospects | B33: =B30*B31 -> 5.9294118 | C33: =C30*C31 -> 5.9294118 | D33: =D30*D31 -> 5.9294118 | E33: =E30*E31 -> 5.9294118 | F33: =F30*F31 -> 5.9294118 | G33: =G30*G31 -> 11.858824 | H33: =H30*H31 -> 11.858824 | I33: =I30*I31 -> 11.858824 | ... M33: =M30*M31 -> 5.9294118 | N33: =SUM(B33:M33) -> 100.8 | O33: =O30*O31 -> 1329.1507 | P33: =P30*P31 -> 3555.5329
A34: Conversion rate | B34: 0 | C34: 0 | D34: 0 | E34: 0 | F34: 0 | G34: 0 | H34: 0 | I34: 0 | J34: 0 | K34: 0 | L34: 0 | M34: 0 | N34: =IF(AVERAGE(B34:M34)=0,"n/a",AVERAGE(B34:M34)) -> n/a
A35: Net New Customers | B35: =B30*B31 -> 5.9294118 | C35: =C30*C31 -> 5.9294118 | D35: =D30*D31 -> 5.9294118 | E35: =E30*E31 -> 5.9294118 | F35: =F30*F31 -> 5.9294118 | G35: =G30*G31 -> 11.858824 | H35: =H30*H31 -> 11.858824 | I35: =I30*I31 -> 11.858824 | ... M35: =M30*M31 -> 5.9294118 | N35: =SUM(B35:M35) -> 100.8 | O35: 0 | P35: 0
A36: Total customers | B36: =B35 -> 5.9294118 | C36: =B36+C35 -> 11.858824 | D36: =C36+D35 -> 17.788235 | E36: =D36+E35 -> 23.717647 | F36: =E36+F35 -> 29.647059 | G36: =F36+G35 -> 41.505882 | H36: =G36+H35 -> 53.364706 | I36: =H36+I35 -> 65.223529 | J36: =I36+J35 -> 77.082353 | ... M36: =L36+M35 -> 100.8 | N36: =M36 -> 100.8 | O36: =N36+O35 -> 100.8 | P36: =O36+P35 -> 100.8
A37: Total Conversion sales & Marketing Expense | B37: =B20+B23+B26+B29 -> 1940 | C37: =C20+C23+C26+C29 -> 1940 | D37: =D20+D23+D26+D29 -> 1940 | E37: =E20+E23+E26+E29 -> 1940 | F37: =F20+F23+F26+F29 -> 1940 | G37: =G20+G23+G26+G29 -> 2240 | H37: =H20+H23+H26+H29 -> 2240 | I37: =I20+I23+I26+I29 -> 2240 | ... M37: =M20+M23+M26+M29 -> 1940 | N37: =N20+N23+N26+#REF!+N29+N32 -> #REF! | O37: =O20+O23+O26+#REF!+O29+O32 -> #REF! | P37: =P20+P23+P26+#REF!+P29+P32 -> #REF!
A39: Total Sales & Marketing Expenses | B39: =B16+B37 -> 3880 | C39: =C16+C37 -> 3880 | D39: =D16+D37 -> 3880 | E39: =E16+E37 -> 3880 | F39: =F16+F37 -> 3880 | G39: =G16+G37 -> 4480 | H39: =H16+H37 -> 4480 | I39: =I16+I37 -> 4480 | ... P39: =P16+P37 -> #REF!

Sheet Unit Economics
A1: FitBox
A2: Unit economics
A3: Develop a clear model of revenue.
A4: Provide line items that reflects the units, price of your offering
A5: together with those that are one time purchase or recurring revenue.
A6: Since there are so many variations to revenue models,
A7: Create yours on this worksheet and be sure that the bottom line
A8: revenue number is reflected in the monthly and annual sums
A9: highlighted in yellow. These will be referenced in the P&L worksheet.
B10: Revenue Streams | G10: Cost of Goods Sold (COGS) | L10: Avg Customer Churn Rate
B11: Initial Purchase | D11: Monthly Recurring | G11: Initial COGS | I11: Monthly Recurring | L11: 0.1
A12: Offering description | B12: Price | C12: Unit | D12: Price | E12: Unit | G12: Cost | H12: Unit | I12: Cost | J12: Unit
A13: FitBox Gym Machine + Free Mobile App | B13: 69.99 | C13: per machine | D13: 0 | E13: per customer | G13: 30 | H13: per machine | I13: 0 | J13: per customer
A14: Premium Model for the Mobile App | B14: 0 | C14: per machine | D14: 14.99 | E14: per customer | G14: 0 | H14: per machine | I14: 1 | J14: per customer
A18: Customers | B18: =SalesMktg!B8 -> 45505 | C18: =SalesMktg!C8 -> 45536 | D18: =SalesMktg!D8 -> 45566 | E18: =SalesMktg!E8 -> 45597 | F18: =SalesMktg!F8 -> 45627 | G18: =SalesMktg!G8 -> 45658 | H18: =SalesMktg!H8 -> 45689 | I18: =SalesMktg!I8 -> 45717 | ... P18: =SalesMktg!P8 -> 2026-27
A19: New customers | B19: =SalesMktg!B42 -> 0 | C19: =SalesMktg!C42 -> 0 | D19: =SalesMktg!D42 -> 0 | E19: =SalesMktg!E42 -> 0 | F19: =SalesMktg!F42 -> 0 | G19: =SalesMktg!G42 -> 0 | H19: =SalesMktg!H42 -> 0 | I19: =SalesMktg!I42 -> 0 | ... M19: =SalesMktg!M42 -> 0 | N19: =SUM(B19:M19) -> 0 | O19: =SalesMktg!O42 -> 0 | P19: =SalesMktg!P42 -> 0
A20: Existing cusomters | B20: 0 | C20: =B19*(1-'Unit Economics'!$L$11) -> 0 | D20: =C19*(1-'Unit Economics'!$L$11) -> 0 | E20: =D19*(1-'Unit Economics'!$L$11) -> 0 | F20: =E19*(1-'Unit Economics'!$L$11) -> 0 | G20: =F19*(1-'Unit Economics'!$L$11) -> 0 | H20: =G19*(1-'Unit Economics'!$L$11) -> 0 | I20: =H19*(1-'Unit Economics'!$L$11) -> 0 | J20: =I19*(1-'Unit Economics'!$L$11) -> 0 | ... N20: =M19*(1-'Unit Economics'!$L$11) -> 0 | O20: =N20*(1-$L$11) -> 0 | P20: =O20*(1-$L$11) -> 0
A22: Revenue
A23: =$A13 -> FitBox Gym Machine + Free Mobile App | B23: =($B13*B$19)+($D13*B$20) -> 0 | C23: =($B13*C$19)+($D13*C$20) -> 0 | D23: =($B13*D$19)+($D13*D$20) -> 0 | E23: =($B13*E$19)+($D13*E$20) -> 0 | F23: =($B13*F$19)+($D13*F$20) -> 0 | G23: =($B13*G$19)+($D13*G$20) -> 0 | H23: =($B13*H$19)+($D13*H$20) -> 0 | I23: =($B13*I$19)+($D13*I$20) -> 0 | ... M23: =($B13*M$19)+($D13*M$20) -> 0 | N23: =SUM(B23:M23) -> 0 | O23: =($B13*O$19)+($D13*O$20) -> 0 | P23: =($B13*P$19)+($D13*P$20) -> 0
A24: =$A14 -> Premium Model for the Mobile App | B24: =($B14*B$19)+($D14*B$20) -> 0 | C24: =($B14*C$19)+($D14*C$20) -> 0 | D24: =($B14*D$19)+($D14*D$20) -> 0 | E24: =($B14*E$19)+($D14*E$20) -> 0 | F24: =($B14*F$19)+($D14*F$20) -> 0 | G24: =($B14*G$19)+($D14*G$20) -> 0 | H24: =($B14*H$19)+($D14*H$20) -> 0 | I24: =($B14*I$19)+($D14*I$20) -> 0 | ... M24: =($B14*M$19)+($D14*M$20) -> 0 | N24: =SUM(B24:M24) -> 0 | O24: =($B14*O$19)+($D14*O$20) -> 0 | P24: =($B14*P$19)+($D14*P$20) -> 0
A25: =$A15 -> 0 | B25: =($B15*B$19)+($D15*B$20) -> 0 | C25: =($B15*C$19)+($D15*C$20) -> 0 | D25: =($B15*D$19)+($D15*D$20) -> 0 | E25: =($B15*E$19)+($D15*E$20) -> 0 | F25: =($B15*F$19)+($D15*F$20) -> 0 | G25: =($B15*G$19)+($D15*G$20) -> 0 | H25: =($B15*H$19)+($D15*H$20) -> 0 | I25: =($B15*I$19)+($D15*I$20) -> 0 | ... M25: =($B15*M$19)+($D15*M$20) -> 0 | N25: =SUM(B25:M25) -> 0 | O25: =($B15*O$19)+($D15*O$20) -> 0 | P25: =($B15*P$19)+($D15*P$20) -> 0
A26: =$A16 -> 0 | B26: =($B16*B$19)+($D16*B$20) -> 0 | C26: =($B16*C$19)+($D16*C$20) -> 0 | D26: =($B16*D$19)+($D16*D$20) -> 0 | E26: =($B16*E$19)+($D16*E$20) -> 0 | F26: =($B16*F$19)+($D16*F$20) -> 0 | G26: =($B16*G$19)+($D16*G$20) -> 0 | H26: =($B16*H$19)+($D16*H$20) -> 0 | I26: =($B16*I$19)+($D16*I$20) -> 0 | ... M26: =($B16*M$19)+($D16*M$20) -> 0 | N26: =SUM(B26:M26) -> 0 | O26: =($B16*O$19)+($D16*O$20) -> 0 | P26: =($B16*P$19)+($D16*P$20) -> 0
A28: Total Revenue | B28: =SUM(B23:B26) -> 0 | C28: =SUM(C23:C26) -> 0 | D28: =SUM(D23:D26) -> 0 | E28: =SUM(E23:E26) -> 0 | F28: =SUM(F23:F26) -> 0 | G28: =SUM(G23:G26) -> 0 | H28: =SUM(H23:H26) -> 0 | I28: =SUM(I23:I26) -> 0 | ... P28: =SUM(P23:P26) -> 0
A30: COGS
A31: =$A13 -> FitBox Gym Machine + Free Mobile App | B31: =($G13*B$19)+($I13*B$20) -> 0 | C31: =($G13*C$19)+($I13*C$20) -> 0 | D31: =($G13*D$19)+($I13*D$20) -> 0 | E31: =($G13*E$19)+($I13*E$20) -> 0 | F31: =($G13*F$19)+($I13*F$20) -> 0 | G31: =($G13*G$19)+($I13*G$20) -> 0 | H31: =($G13*H$19)+($I13*H$20) -> 0 | I31: =($G13*I$19)+($I13*I$20) -> 0 | ... M31: =($G13*M$19)+($I13*M$20) -> 0 | N31: =SUM(B31:M31) -> 0 | O31: =($G13*O$19)+($I13*O$20) -> 0 | P31: =($G13*P$19)+($I13*P$20) -> 0
A32: =$A14 -> Premium Model for the Mobile App | B32: =($G14*B$19)+($I14*B$20) -> 0 | C32: =($G14*C$19)+($I14*C$20) -> 0 | D32: =($G14*D$19)+($I14*D$20) -> 0 | E32: =($G14*E$19)+($I14*E$20) -> 0 | F32: =($G14*F$19)+($I14*F$20) -> 0 | G32: =($G14*G$19)+($I14*G$20) -> 0 | H32: =($G14*H$19)+($I14*H$20) -> 0 | I32: =($G14*I$19)+($I14*I$20) -> 0 | ... M32: =($G14*M$19)+($I14*M$20) -> 0 | N32: =SUM(B32:M32) -> 0 | O32: =($G14*O$19)+($I14*O$20) -> 0 | P32: =($G14*P$19)+($I14*P$20) -> 0
A33: =$A15 -> 0 | B33: =($G15*B$19)+($I15*B$20) -> 0 | C33: =($G15*C$19)+($I15*C$20) -> 0 | D33: =($G15*D$19)+($I15*D$20) -> 0 | E33: =($G15*E$19)+($I15*E$20) -> 0 | F33: =($G15*F$19)+($I15*F$20) -> 0 | G33: =($G15*G$19)+($I15*G$20) -> 0 | H33: =($G15*H$19)+($I15*H$20) -> 0 | I33: =($G15*I$19)+($I15*I$20) -> 0 | ... M33: =($G15*M$19)+($I15*M$20) -> 0 | N33: =SUM(B33:M33) -> 0 | O33: =($G15*O$19)+($I15*O$20) -> 0 | P33: =($G15*P$19)+($I15*P$20) -> 0
A34: =$A16 -> 0 | B34: =($G16*B$19)+($I16*B$20) -> 0 | C34: =($G16*C$19)+($I16*C$20) -> 0 | D34: =($G16*D$19)+($I16*D$20) -> 0 | E34: =($G16*E$19)+($I16*E$20) -> 0 | F34: =($G16*F$19)+($I16*F$20) -> 0 | G34: =($G16*G$19)+($I16*G$20) -> 0 | H34: =($G16*H$19)+($I16*H$20) -> 0 | I34: =($G16*I$19)+($I16*I$20) -> 0 | ... M34: =($G16*M$19)+($I16*M$20) -> 0 | N34: =SUM(B34:M34) -> 0 | O34: =($G16*O$19)+($I16*O$20) -> 0 | P34: =($G16*P$19)+($I16*P$20) -> 0
A36: Total COGS | B36: =SUM(B31:B34) -> 0 | C36: =SUM(C31:C34) -> 0 | D36: =SUM(D31:D34) -> 0 | E36: =SUM(E31:E34) -> 0 | F36: =SUM(F31:F34) -> 0 | G36: =SUM(G31:G34) -> 0 | H36: =SUM(H31:H34) -> 0 | I36: =SUM(I31:I34) -> 0 | ... P36: =SUM(P31:P34) -> 0
N37: =SUM(B37:M37) -> 0

Sheet P&L
A1: =Venture -> FitBox
A2: Income Statement
B3: ='Unit Economics'!B18 -> 45505 | C3: ='Unit Economics'!C18 -> 45536 | D3: ='Unit Economics'!D18 -> 45566 | E3: ='Unit Economics'!E18 -> 45597 | F3: ='Unit Economics'!F18 -> 45627 | G3: ='Unit Economics'!G18 -> 45658 | H3: ='Unit Economics'!H18 -> 45689 | I3: ='Unit Economics'!I18 -> 45717 | ... P3: ='Unit Economics'!P18 -> 2026-27
A4: Net Revenues | B4: ='Unit Economics'!B28 -> 0 | C4: ='Unit Economics'!C28 -> 0 | D4: ='Unit Economics'!D28 -> 0 | E4: ='Unit Economics'!E28 -> 0 | F4: ='Unit Economics'!F28 -> 0 | G4: ='Unit Economics'!G28 -> 0 | H4: ='Unit Economics'!H28 -> 0 | I4: ='Unit Economics'!I28 -> 0 | ... P4: ='Unit Economics'!P28 -> 0
A6: Costs of Goods Sold | B6: ='Unit Economics'!B36 -> 0 | C6: ='Unit Economics'!C36 -> 0 | D6: ='Unit Economics'!D36 -> 0 | E6: ='Unit Economics'!E36 -> 0 | F6: ='Unit Economics'!F36 -> 0 | G6: ='Unit Economics'!G36 -> 0 | H6: ='Unit Economics'!H36 -> 0 | I6: ='Unit Economics'!I36 -> 0 | ... P6: ='Unit Economics'!P36 -> 0
A7: % of Revenues | B7: =IF(B4=0,"n/a",B6/B4) -> n/a | C7: =IF(C4=0,"n/a",C6/C4) -> n/a | D7: =IF(D4=0,"n/a",D6/D4) -> n/a | E7: =IF(E4=0,"n/a",E6/E4) -> n/a | F7: =IF(F4=0,"n/a",F6/F4) -> n/a | G7: =IF(G4=0,"n/a",G6/G4) -> n/a | H7: =IF(H4=0,"n/a",H6/H4) -> n/a | I7: =IF(I4=0,"n/a",I6/I4) -> n/a | ... P7: =IF(P4=0,"n/a",P6/P4) -> n/a
A9: Gross Profit | B9: =B4-B6 -> 0 | C9: =C4-C6 -> 0 | D9: =D4-D6 -> 0 | E9: =E4-E6 -> 0 | F9: =F4-F6 -> 0 | G9: =G4-G6 -> 0 | H9: =H4-H6 -> 0 | I9: =I4-I6 -> 0 | ... P9: =P4-P6 -> 0
A10: % of Revenues | B10: =IF(B4=0,"n/a",B9/B4) -> n/a | C10: =IF(C4=0,"n/a",C9/C4) -> n/a | D10: =IF(D4=0,"n/a",D9/D4) -> n/a | E10: =IF(E4=0,"n/a",E9/E4) -> n/a | F10: =IF(F4=0,"n/a",F9/F4) -> n/a | G10: =IF(G4=0,"n/a",G9/G4) -> n/a | H10: =IF(H4=0,"n/a",H9/H4) -> n/a | I10: =IF(I4=0,"n/a",I9/I4) -> n/a | ... P10: =IF(P4=0,"n/a",P9/P4) -> n/a
A12: Operating Expenses
A13: Sales & Marketing | B13: =SalesMktg!B39 -> 3880 | C13: =SalesMktg!C39 -> 3880 | D13: =SalesMktg!D39 -> 3880 | E13: =SalesMktg!E39 -> 3880 | F13: =SalesMktg!F39 -> 3880 | G13: =SalesMktg!G39 -> 4480 | H13: =SalesMktg!H39 -> 4480 | I13: =SalesMktg!I39 -> 4480 | ... P13: =SalesMktg!P39 -> #REF!
A14: Research & Development | B14: 15000 | C14: 15000 | D14: 15000 | E14: 15000 | F14: 15000 | G14: 16000 | H14: 16000 | I14: 16000 | J14: 16000 | K14: 16000 | L14: 16000 | M14: 16000 | N14: 18000 | O14: 20000 | P14: 22000
A15: General and Administration | B15: 5000 | C15: 5000 | D15: 5000 | E15: 5000 | F15: 5000 | G15: 5000 | H15: 5000 | I15: 5000 | J15: 5000 | K15: 5000 | L15: 5000 | M15: 5000 | N15: =SUM(B15:M15) -> 60000 | O15: 70000 | P15: 80000
A16: Total Operating Expenses | B16: =SUM(B13:B15) -> 23880 | C16: =SUM(C13:C15) -> 23880 | D16: =SUM(D13:D15) -> 23880 | E16: =SUM(E13:E15) -> 23880 | F16: =SUM(F13:F15) -> 23880 | G16: =SUM(G13:G15) -> 25480 | H16: =SUM(H13:H15) -> 25480 | I16: =SUM(I13:I15) -> 25480 | ... P16: =SUM(P13:P15) -> #REF!
A17: % of Revenues | B17: =IF(B$4=0,"n/a",B16/B$4) -> n/a | C17: =IF(C$4=0,"n/a",C16/C$4) -> n/a | D17: =IF(D$4=0,"n/a",D16/D$4) -> n/a | E17: =IF(E$4=0,"n/a",E16/E$4) -> n/a | F17: =IF(F$4=0,"n/a",F16/F$4) -> n/a | G17: =IF(G$4=0,"n/a",G16/G$4) -> n/a | H17: =IF(H$4=0,"n/a",H16/H$4) -> n/a | I17: =IF(I$4=0,"n/a",I16/I$4) -> n/a | ... P17: =IF(P$4=0,"n/a",P16/P$4) -> n/a
A19: Earnings from Operations | B19: =B9-B16 -> -23880 | C19: =C9-C16 -> -23880 | D19: =D9-D16 -> -23880 | E19: =E9-E16 -> -23880 | F19: =F9-F16 -> -23880 | G19: =G9-G16 -> -25480 | H19: =H9-H16 -> -25480 | I19: =I9-I16 -> -25480 | ... P19: =P9-P16 -> #REF!
A21: Taxes (enter tax rate below; 0 if no Earnings) | B21: =IF(B19*$A$22<0,0,B19*$A$22) -> 0 | C21: =IF(C19*$A$22<0,0,C19*$A$22) -> 0 | D21: =IF(D19*$A$22<0,0,D19*$A$22) -> 0 | E21: =IF(E19*$A$22<0,0,E19*$A$22) -> 0 | F21: =IF(F19*$A$22<0,0,F19*$A$22) -> 0 | G21: =IF(G19*$A$22<0,0,G19*$A$22) -> 0 | H21: =IF(H19*$A$22<0,0,H19*$A$22) -> 0 | I21: =IF(I19*$A$22<0,0,I19*$A$22) -> 0 | ... P21: =IF(P19*$A$22<0,0,P19*$A$22) -> #REF!
A22: 0.25
A23: Net Earnings (Loss) | B23: =B19-B21 -> -23880 | C23: =C19-C21 -> -23880 | D23: =D19-D21 -> -23880 | E23: =E19-E21 -> -23880 | F23: =F19-F21 -> -23880 | G23: =G19-G21 -> -25480 | H23: =H19-H21 -> -25480 | I23: =I19-I21 -> -25480 | ... P23: =P19-P21 -> #REF!
A24: % of Revenues | B24: =IF(B$4=0,"n/a",B23/B$4) -> n/a | C24: =IF(C$4=0,"n/a",C23/C$4) -> n/a | D24: =IF(D$4=0,"n/a",D23/D$4) -> n/a | E24: =IF(E$4=0,"n/a",E23/E$4) -> n/a | F24: =IF(F$4=0,"n/a",F23/F$4) -> n/a | G24: =IF(G$4=0,"n/a",G23/G$4) -> n/a | H24: =IF(H$4=0,"n/a",H23/H$4) -> n/a | I24: =IF(I$4=0,"n/a",I23/I$4) -> n/a | ... P24: =IF(P$4=0,"n/a",P23/P$4) -> n/a
